headpose_estimation/WHENet.h5
headpose_estimation/__init__.py
headpose_estimation/headpose.py
headpose_estimation/utils.py
headpose_estimation/whenet.py
headpose_estimation/face_detector/__init__.py
headpose_estimation/face_detector/demo.py
headpose_estimation/face_detector/retinaface.py
headpose_estimation/face_detector/commons/__init__.py
headpose_estimation/face_detector/commons/postprocess.py
headpose_estimation/face_detector/commons/preprocess.py
headpose_estimation/face_detector/model/__init__.py
headpose_estimation/face_detector/model/retinaface_model.py
headpose_detection-0.0.4.dist-info/METADATA
headpose_detection-0.0.4.dist-info/WHEEL
headpose_detection-0.0.4.dist-info/top_level.txt
headpose_detection-0.0.4.dist-info/RECORD
