Metadata-Version: 2.1
Name: headpose-detection
Version: 0.0.4
Summary: Head pose estimation module
Home-page: https://github.com/geekysethi/headpose_estimation
Author: Ashish Sethi
Author-email: <ashish18024@iiitd.ac.in>
Keywords: python,image,face detection,headpose estimation,machine learning,computer vision
Requires-Dist: efficientnet
